build/lib/build/lib/build/lib/fax/__init__.py
build/lib/build/lib/build/lib/fax/config.py
build/lib/build/lib/build/lib/fax/converge.py
build/lib/build/lib/build/lib/fax/loop.py
build/lib/build/lib/build/lib/fax/loop_test.py
build/lib/build/lib/build/lib/fax/math.py
build/lib/build/lib/build/lib/fax/test_util.py
build/lib/build/lib/build/lib/fax/competitive/cg.py
build/lib/build/lib/build/lib/fax/competitive/cg_test.py
build/lib/build/lib/build/lib/fax/competitive/cga.py
build/lib/build/lib/build/lib/fax/competitive/cga_test.py
build/lib/build/lib/build/lib/fax/competitive/extragradient.py
build/lib/build/lib/build/lib/fax/competitive/extragradient_test.py
build/lib/build/lib/build/lib/fax/constrained/__init__.py
build/lib/build/lib/build/lib/fax/constrained/constrained.py
build/lib/build/lib/build/lib/fax/constrained/constrained_test.py
build/lib/build/lib/build/lib/fax/implicit/__init__.py
build/lib/build/lib/build/lib/fax/implicit/twophase.py
build/lib/build/lib/build/lib/fax/implicit/twophase_test.py
build/lib/build/lib/build/lib/venv/bin/activate_this.py
build/lib/build/lib/fax/__init__.py
build/lib/build/lib/fax/config.py
build/lib/build/lib/fax/converge.py
build/lib/build/lib/fax/loop.py
build/lib/build/lib/fax/loop_test.py
build/lib/build/lib/fax/math.py
build/lib/build/lib/fax/test_util.py
build/lib/build/lib/fax/competitive/cg.py
build/lib/build/lib/fax/competitive/cg_test.py
build/lib/build/lib/fax/competitive/cga.py
build/lib/build/lib/fax/competitive/cga_test.py
build/lib/build/lib/fax/competitive/extragradient.py
build/lib/build/lib/fax/competitive/extragradient_test.py
build/lib/build/lib/fax/constrained/__init__.py
build/lib/build/lib/fax/constrained/constrained.py
build/lib/build/lib/fax/constrained/constrained_test.py
build/lib/build/lib/fax/implicit/__init__.py
build/lib/build/lib/fax/implicit/twophase.py
build/lib/build/lib/fax/implicit/twophase_test.py
build/lib/build/lib/venv/bin/activate_this.py
build/lib/build/lib/venv/bin/rst2html.py
jax_fixedpoint_test_manueldelverme-0.0.4.dist-info/LICENSE
jax_fixedpoint_test_manueldelverme-0.0.4.dist-info/METADATA
jax_fixedpoint_test_manueldelverme-0.0.4.dist-info/WHEEL
jax_fixedpoint_test_manueldelverme-0.0.4.dist-info/top_level.txt
jax_fixedpoint_test_manueldelverme-0.0.4.dist-info/RECORD
