Metadata-Version: 2.1
Name: jax-fixedpoint-test-manueldelverme
Version: 0.0.4
Summary: Implicit and competitive differentiation in JAX.
Home-page: UNKNOWN
Author: Clement Gehring
Author-email: fax-dev@gehring.io
License: MIT License
Platform: UNKNOWN
Classifier: Intended Audience :: Developers
Classifier: Intended Audience :: Science/Research
Classifier: License :: OSI Approved :: MIT License
Classifier: Operating System :: MacOS :: MacOS X
Classifier: Operating System :: Microsoft :: Windows
Classifier: Operating System :: POSIX
Classifier: Programming Language :: C++
Classifier: Programming Language :: Python :: 3
Classifier: Topic :: Scientific/Engineering :: Artificial Intelligence
Requires-Python: >=3.5
Requires-Dist: numpy
Requires-Dist: scipy
Requires-Dist: absl-py
Requires-Dist: jax
Requires-Dist: jaxlib
Requires-Dist: hypothesis
